[
  {
    "match-id": "2384797636",
    "hero": 25,
    "date": 1464042896,
    "result": true,
    "IMR": 4347.034414140175,
    "players": [
      {
        "hero": 109,
        "name": "Stone"
      },
      {
        "hero": 13,
        "name": "Md5K"
      },
      {
        "hero": 22,
        "name": "Anusbob"
      },
      {
        "hero": 5,
        "name": "HOLD THE DOOR! :("
      },
      {
        "hero": 26,
        "name": "Keck³"
      },
      {
        "hero": 9,
        "name": "Tsipe"
      },
      {
        "hero": 25,
        "name": "Zera | wisdota.com"
      },
      {
        "hero": 39,
        "name": "vhjrtsbgkg"
      },
      {
        "hero": 85,
        "name": "Szron"
      },
      {
        "hero": 93,
        "name": "''MAH NIGGA''"
      }
    ],
    "ratings": [
      {
        "attribute": "Mechanics",
        "rating": 4327.97576062387,
        "skills": {
          "n-checks": 1.0939048849126336,
          "camera-jumps": 216,
          "movement-per-minute": 895.8547380774133
        }
      },
      {
        "attribute": "Farming",
        "rating": 3966.1407307055943,
        "skills": {
          "GPM": 329,
          "XPM": 410,
          "missed-free-lasthits": 30,
          "percent-of-contested-lasthits-gotten": 0.3541666666666667
        }
      },
      {
        "attribute": "Fighting",
        "rating": 3966.1407307055943,
        "skills": {
          "kills": 7,
          "deaths": 11,
          "fights": 46
        }
      }
    ]
  },
  {
    "match-id": "2384797636",
    "hero": 62,
    "date": 1464042896,
    "result": true,
    "IMR": 4347.034414140175,
    "players": [
      {
        "hero": 109,
        "name": "Stone"
      },
      {
        "hero": 13,
        "name": "Md5K"
      },
      {
        "hero": 22,
        "name": "Anusbob"
      },
      {
        "hero": 5,
        "name": "HOLD THE DOOR! :("
      },
      {
        "hero": 26,
        "name": "Keck³"
      },
      {
        "hero": 9,
        "name": "Tsipe"
      },
      {
        "hero": 25,
        "name": "Zera | wisdota.com"
      },
      {
        "hero": 39,
        "name": "vhjrtsbgkg"
      },
      {
        "hero": 85,
        "name": "Szron"
      },
      {
        "hero": 93,
        "name": "''MAH NIGGA''"
      }
    ],
    "ratings": [
      {
        "attribute": "Mechanics",
        "rating": 4327.97576062387,
        "skills": {
          "n-checks": 1.0939048849126336,
          "camera-jumps": 216,
          "movement-per-minute": 895.8547380774133
        }
      },
      {
        "attribute": "Farming",
        "rating": 3966.1407307055943,
        "skills": {
          "GPM": 329,
          "XPM": 410,
          "missed-free-lasthits": 30,
          "percent-of-contested-lasthits-gotten": 0.3541666666666667
        }
      },
      {
        "attribute": "Fighting",
        "rating": 3966.1407307055943,
        "skills": {
          "kills": 7,
          "deaths": 11,
          "fights": 46
        }
      }
    ]
  }
]

